{"nhits": 43, "parameters": {"dataset": ["arome-0025-sp1_sp2"], "timezone": "UTC", "rows": 100, "start": 0, "sort": ["forecast"], "format": "json", "geofilter.distance": ["43.60, 1.45, 100"]}, "records": [{"datasetid": "arome-0025-sp1_sp2", "recordid": "arome_0025_sp1_sp2_sp3_lastgrib2-12966864", "fields": {"surface_net_thermal_radiation": -12374464.0, "downward_short_wave_radiation_flux": 31575840.0, "2_metre_temperature": 9.784020999999996, "dist": "0.0", "minimum_temperature_at_2_metres": 9.783044000000018, "surface_net_solar_radiation": 27929916.0, "timestamp": "2021-03-17T00:00:00+00:00", "surface_latent_heat_flux": -2991456.0, "total_water_precipitation": 0.414063, "relative_humidity": 48.607468, "surface_sensible_heat_flux": -15753008.0, "position": [43.6, 1.45], "wind_speed": 4.757027, "forecast": "2021-03-18T18:00:00+00:00", "maximum_temperature_at_2_metres": 10.314630000000022}, "geometry": {"type": "Point", "coordinates": [1.45, 43.6]}, "record_timestamp": "2021-03-17T00:00:00+00:00"}, {"datasetid": "arome-0025-sp1_sp2", "recordid": "arome_0025_sp1_sp2_sp3_lastgrib2-12966863", "fields": {"surface_net_thermal_radiation": -12067840.0, "downward_short_wave_radiation_flux": 31391192.0, "2_metre_temperature": 10.324945000000014, "dist": "0.0", "minimum_temperature_at_2_metres": 10.313226000000043, "surface_net_solar_radiation": 27765934.0, "timestamp": "2021-03-17T00:00:00+00:00", "surface_latent_heat_flux": -2961648.0, "total_water_precipitation": 0.414063, "relative_humidity": 47.223465, "surface_sensible_heat_flux": -15550144.0, "position": [43.6, 1.45], "wind_speed": 4.983509, "forecast": "2021-03-18T17:00:00+00:00", "maximum_temperature_at_2_metres": 10.704736000000025}, "geometry": {"type": "Point", "coordinates": [1.45, 43.6]}, "record_timestamp": "2021-03-17T00:00:00+00:00"}, {"datasetid": "arome-0025-sp1_sp2", "recordid": "arome_0025_sp1_sp2_sp3_lastgrib2-12966862", "fields": {"surface_net_thermal_radiation": -11698496.0, "downward_short_wave_radiation_flux": 30748784.0, "2_metre_temperature": 10.716272000000004, "dist": "0.0", "minimum_temperature_at_2_metres": 10.633263999999997, "surface_net_solar_radiation": 27198528.0, "timestamp": "2021-03-17T00:00:00+00:00", "surface_latent_heat_flux": -2904896.0, "total_water_precipitation": 0.414063, "relative_humidity": 46.68882, "surface_sensible_heat_flux": -15133840.0, "position": [43.6, 1.45], "wind_speed": 5.126629, "forecast": "2021-03-18T16:00:00+00:00", "maximum_temperature_at_2_metres": 10.825220000000002}, "geometry": {"type": "Point", "coordinates": [1.45, 43.6]}, "record_timestamp": "2021-03-17T00:00:00+00:00"}, {"datasetid": "arome-0025-sp1_sp2", "recordid": "arome_0025_sp1_sp2_sp3_lastgrib2-12966861", "fields": {"surface_net_thermal_radiation": -11294288.0, "downward_short_wave_radiation_flux": 29679080.0, "2_metre_temperature": 10.726984000000016, "dist": "0.0", "minimum_temperature_at_2_metres": 10.548547000000042, "surface_net_solar_radiation": 26251338.0, "timestamp": "2021-03-17T00:00:00+00:00", "surface_latent_heat_flux": -2832624.0, "total_water_precipitation": 0.414063, "relative_humidity": 46.230255, "surface_sensible_heat_flux": -14525744.0, "position": [43.6, 1.45], "wind_speed": 4.90222, "forecast": "2021-03-18T15:00:00+00:00", "maximum_temperature_at_2_metres": 10.764673000000016}, "geometry": {"type": "Point", "coordinates": [1.45, 43.6]}, "record_timestamp": "2021-03-17T00:00:00+00:00"}, {"datasetid": "arome-0025-sp1_sp2", "recordid": "arome_0025_sp1_sp2_sp3_lastgrib2-12966860", "fields": {"surface_net_thermal_radiation": -10852880.0, "downward_short_wave_radiation_flux": 28266360.0, "2_metre_temperature": 10.56514900000002, "dist": "0.0", "minimum_temperature_at_2_metres": 10.564172000000042, "surface_net_solar_radiation": 25000068.0, "timestamp": "2021-03-17T00:00:00+00:00", "surface_latent_heat_flux": -2750032.0, "total_water_precipitation": 0.414063, "relative_humidity": 46.869202, "surface_sensible_heat_flux": -13742768.0, "position": [43.6, 1.45], "wind_speed": 4.84496, "forecast": "2021-03-18T14:00:00+00:00", "maximum_temperature_at_2_metres": 10.805383000000006}, "geometry": {"type": "Point", "coordinates": [1.45, 43.6]}, "record_timestamp": "2021-03-17T00:00:00+00:00"}, {"datasetid": "arome-0025-sp1_sp2", "recordid": "arome_0025_sp1_sp2_sp3_lastgrib2-12966859", "fields": {"surface_net_thermal_radiation": -10320928.0, "downward_short_wave_radiation_flux": 26373588.0, "2_metre_temperature": 10.665491000000031, "dist": "0.0", "minimum_temperature_at_2_metres": 10.00631100000004, "surface_net_solar_radiation": 23324138.0, "timestamp": "2021-03-17T00:00:00+00:00", "surface_latent_heat_flux": -2650992.0, "total_water_precipitation": 0.414063, "relative_humidity": 45.197479, "surface_sensible_heat_flux": -12760576.0, "position": [43.6, 1.45], "wind_speed": 4.575324, "forecast": "2021-03-18T13:00:00+00:00", "maximum_temperature_at_2_metres": 10.663538000000017}, "geometry": {"type": "Point", "coordinates": [1.45, 43.6]}, "record_timestamp": "2021-03-17T00:00:00+00:00"}, {"datasetid": "arome-0025-sp1_sp2", "recordid": "arome_0025_sp1_sp2_sp3_lastgrib2-12966858", "fields": {"surface_net_thermal_radiation": -9743936.0, "downward_short_wave_radiation_flux": 24036234.0, "2_metre_temperature": 9.982079999999996, "dist": "0.0", "minimum_temperature_at_2_metres": 9.048669000000018, "surface_net_solar_radiation": 21252984.0, "timestamp": "2021-03-17T00:00:00+00:00", "surface_latent_heat_flux": -2547712.0, "total_water_precipitation": 0.414063, "relative_humidity": 50.450516, "surface_sensible_heat_flux": -11647792.0, "position": [43.6, 1.45], "wind_speed": 4.315879, "forecast": "2021-03-18T12:00:00+00:00", "maximum_temperature_at_2_metres": 9.98403300000001}, "geometry": {"type": "Point", "coordinates": [1.45, 43.6]}, "record_timestamp": "2021-03-17T00:00:00+00:00"}, {"datasetid": "arome-0025-sp1_sp2", "recordid": "arome_0025_sp1_sp2_sp3_lastgrib2-12966857", "fields": {"surface_net_thermal_radiation": -9168096.0, "downward_short_wave_radiation_flux": 21725892.0, "2_metre_temperature": 9.063959000000011, "dist": "0.0", "minimum_temperature_at_2_metres": 7.630884000000037, "surface_net_solar_radiation": 19206550.0, "timestamp": "2021-03-17T00:00:00+00:00", "surface_latent_heat_flux": -2455968.0, "total_water_precipitation": 0.414063, "relative_humidity": 56.489044, "surface_sensible_heat_flux": -10593264.0, "position": [43.6, 1.45], "wind_speed": 3.489315, "forecast": "2021-03-18T11:00:00+00:00", "maximum_temperature_at_2_metres": 9.064935000000048}, "geometry": {"type": "Point", "coordinates": [1.45, 43.6]}, "record_timestamp": "2021-03-17T00:00:00+00:00"}, {"datasetid": "arome-0025-sp1_sp2", "recordid": "arome_0025_sp1_sp2_sp3_lastgrib2-12966856", "fields": {"surface_net_thermal_radiation": -8551904.0, "downward_short_wave_radiation_flux": 19321184.0, "2_metre_temperature": 7.616937000000007, "dist": "0.0", "minimum_temperature_at_2_metres": 6.239526000000012, "surface_net_solar_radiation": 17079660.0, "timestamp": "2021-03-17T00:00:00+00:00", "surface_latent_heat_flux": -2377696.0, "total_water_precipitation": 0.414063, "relative_humidity": 63.412476, "surface_sensible_heat_flux": -9632538.0, "position": [43.6, 1.45], "wind_speed": 2.764757, "forecast": "2021-03-18T10:00:00+00:00", "maximum_temperature_at_2_metres": 7.62670300000002}, "geometry": {"type": "Point", "coordinates": [1.45, 43.6]}, "record_timestamp": "2021-03-17T00:00:00+00:00"}, {"datasetid": "arome-0025-sp1_sp2", "recordid": "arome_0025_sp1_sp2_sp3_lastgrib2-12966855", "fields": {"surface_net_thermal_radiation": -8013312.0, "downward_short_wave_radiation_flux": 17311516.0, "2_metre_temperature": 6.196161000000018, "dist": "0.0", "minimum_temperature_at_2_metres": 5.019617000000039, "surface_net_solar_radiation": 15307804.0, "timestamp": "2021-03-17T00:00:00+00:00", "surface_latent_heat_flux": -2305296.0, "total_water_precipitation": 0.414063, "relative_humidity": 70.228775, "surface_sensible_heat_flux": -8906324.0, "position": [43.6, 1.45], "wind_speed": 2.793848, "forecast": "2021-03-18T09:00:00+00:00", "maximum_temperature_at_2_metres": 6.1863950000000045}, "geometry": {"type": "Point", "coordinates": [1.45, 43.6]}, "record_timestamp": "2021-03-17T00:00:00+00:00"}, {"datasetid": "arome-0025-sp1_sp2", "recordid": "arome_0025_sp1_sp2_sp3_lastgrib2-12966854", "fields": {"surface_net_thermal_radiation": -7572720.0, "downward_short_wave_radiation_flux": 15868886.0, "2_metre_temperature": 5.013300000000015, "dist": "0.0", "minimum_temperature_at_2_metres": 4.309412000000009, "surface_net_solar_radiation": 14039773.0, "timestamp": "2021-03-17T00:00:00+00:00", "surface_latent_heat_flux": -2232464.0, "total_water_precipitation": 0.414063, "relative_humidity": 77.788727, "surface_sensible_heat_flux": -8417966.0, "position": [43.6, 1.45], "wind_speed": 3.082276, "forecast": "2021-03-18T08:00:00+00:00", "maximum_temperature_at_2_metres": 5.019159000000002}, "geometry": {"type": "Point", "coordinates": [1.45, 43.6]}, "record_timestamp": "2021-03-17T00:00:00+00:00"}, {"datasetid": "arome-0025-sp1_sp2", "recordid": "arome_0025_sp1_sp2_sp3_lastgrib2-12966853", "fields": {"surface_net_thermal_radiation": -7208144.0, "downward_short_wave_radiation_flux": 15050543.0, "2_metre_temperature": 4.257959000000028, "dist": "0.0", "minimum_temperature_at_2_metres": 3.712549000000024, "surface_net_solar_radiation": 13322462.0, "timestamp": "2021-03-17T00:00:00+00:00", "surface_latent_heat_flux": -2197856.0, "total_water_precipitation": 0.414063, "relative_humidity": 83.643326, "surface_sensible_heat_flux": -8150254.0, "position": [43.6, 1.45], "wind_speed": 2.939836, "forecast": "2021-03-18T07:00:00+00:00", "maximum_temperature_at_2_metres": 4.267725000000041}, "geometry": {"type": "Point", "coordinates": [1.45, 43.6]}, "record_timestamp": "2021-03-17T00:00:00+00:00"}, {"datasetid": "arome-0025-sp1_sp2", "recordid": "arome_0025_sp1_sp2_sp3_lastgrib2-12966852", "fields": {"surface_net_thermal_radiation": -6911584.0, "downward_short_wave_radiation_flux": 14851454.0, "2_metre_temperature": 3.7627200000000016, "dist": "0.0", "minimum_temperature_at_2_metres": 3.7624760000000492, "surface_net_solar_radiation": 13148043.0, "timestamp": "2021-03-17T00:00:00+00:00", "surface_latent_heat_flux": -2203248.0, "total_water_precipitation": 0.414063, "relative_humidity": 87.325806, "surface_sensible_heat_flux": -8053039.0, "position": [43.6, 1.45], "wind_speed": 2.728077, "forecast": "2021-03-18T06:00:00+00:00", "maximum_temperature_at_2_metres": 4.335229000000027}, "geometry": {"type": "Point", "coordinates": [1.45, 43.6]}, "record_timestamp": "2021-03-17T00:00:00+00:00"}, {"datasetid": "arome-0025-sp1_sp2", "recordid": "arome_0025_sp1_sp2_sp3_lastgrib2-12966851", "fields": {"surface_net_thermal_radiation": -6629341.0, "downward_short_wave_radiation_flux": 14850977.0, "2_metre_temperature": 4.361230000000035, "dist": "0.0", "minimum_temperature_at_2_metres": 4.351282000000026, "surface_net_solar_radiation": 13148043.0, "timestamp": "2021-03-17T00:00:00+00:00", "surface_latent_heat_flux": -2224720.0, "total_water_precipitation": 0.414063, "relative_humidity": 85.152168, "surface_sensible_heat_flux": -8039829.0, "position": [43.6, 1.45], "wind_speed": 2.91787, "forecast": "2021-03-18T05:00:00+00:00", "maximum_temperature_at_2_metres": 5.4284000000000106}, "geometry": {"type": "Point", "coordinates": [1.45, 43.6]}, "record_timestamp": "2021-03-17T00:00:00+00:00"}, {"datasetid": "arome-0025-sp1_sp2", "recordid": "arome_0025_sp1_sp2_sp3_lastgrib2-12966850", "fields": {"surface_net_thermal_radiation": -6355267.0, "downward_short_wave_radiation_flux": 14850977.0, "2_metre_temperature": 5.423486000000025, "dist": "0.0", "minimum_temperature_at_2_metres": 5.416832999999997, "surface_net_solar_radiation": 13148043.0, "timestamp": "2021-03-17T00:00:00+00:00", "surface_latent_heat_flux": -2241536.0, "total_water_precipitation": 0.414063, "relative_humidity": 80.166573, "surface_sensible_heat_flux": -8029629.0, "position": [43.6, 1.45], "wind_speed": 2.751972, "forecast": "2021-03-18T04:00:00+00:00", "maximum_temperature_at_2_metres": 6.245752000000039}, "geometry": {"type": "Point", "coordinates": [1.45, 43.6]}, "record_timestamp": "2021-03-17T00:00:00+00:00"}, {"datasetid": "arome-0025-sp1_sp2", "recordid": "arome_0025_sp1_sp2_sp3_lastgrib2-12966849", "fields": {"surface_net_thermal_radiation": -6077409.0, "downward_short_wave_radiation_flux": 14850977.0, "2_metre_temperature": 6.261377000000039, "dist": "0.0", "minimum_temperature_at_2_metres": 6.25356400000004, "surface_net_solar_radiation": 13148043.0, "timestamp": "2021-03-17T00:00:00+00:00", "surface_latent_heat_flux": -2251936.0, "total_water_precipitation": 0.414063, "relative_humidity": 76.642319, "surface_sensible_heat_flux": -8027207.0, "position": [43.6, 1.45], "wind_speed": 2.739602, "forecast": "2021-03-18T03:00:00+00:00", "maximum_temperature_at_2_metres": 6.988550000000032}, "geometry": {"type": "Point", "coordinates": [1.45, 43.6]}, "record_timestamp": "2021-03-17T00:00:00+00:00"}, {"datasetid": "arome-0025-sp1_sp2", "recordid": "arome_0025_sp1_sp2_sp3_lastgrib2-12966848", "fields": {"surface_net_thermal_radiation": -5910586.0, "downward_short_wave_radiation_flux": 14850977.0, "2_metre_temperature": 7.0097900000000095, "dist": "0.0", "minimum_temperature_at_2_metres": 6.9004150000000095, "surface_net_solar_radiation": 13148043.0, "timestamp": "2021-03-17T00:00:00+00:00", "surface_latent_heat_flux": -2248832.0, "total_water_precipitation": 0.404297, "relative_humidity": 70.727196, "surface_sensible_heat_flux": -7985944.0, "position": [43.6, 1.45], "wind_speed": 2.521426, "forecast": "2021-03-18T02:00:00+00:00", "maximum_temperature_at_2_metres": 7.092004000000031}, "geometry": {"type": "Point", "coordinates": [1.45, 43.6]}, "record_timestamp": "2021-03-17T00:00:00+00:00"}, {"datasetid": "arome-0025-sp1_sp2", "recordid": "arome_0025_sp1_sp2_sp3_lastgrib2-12966847", "fields": {"surface_net_thermal_radiation": -5759611.0, "downward_short_wave_radiation_flux": 14850977.0, "2_metre_temperature": 7.111353000000008, "dist": "0.0", "minimum_temperature_at_2_metres": 7.106470000000002, "surface_net_solar_radiation": 13148043.0, "timestamp": "2021-03-17T00:00:00+00:00", "surface_latent_heat_flux": -2246640.0, "total_water_precipitation": 0.40332, "relative_humidity": 69.636108, "surface_sensible_heat_flux": -7958004.0, "position": [43.6, 1.45], "wind_speed": 3.278203, "forecast": "2021-03-18T01:00:00+00:00", "maximum_temperature_at_2_metres": 7.627283000000034}, "geometry": {"type": "Point", "coordinates": [1.45, 43.6]}, "record_timestamp": "2021-03-17T00:00:00+00:00"}, {"datasetid": "arome-0025-sp1_sp2", "recordid": "arome_0025_sp1_sp2_sp3_lastgrib2-12966846", "fields": {"surface_net_thermal_radiation": -5534246.0, "downward_short_wave_radiation_flux": 14850977.0, "2_metre_temperature": 7.633752000000015, "dist": "0.0", "minimum_temperature_at_2_metres": 7.637659000000042, "surface_net_solar_radiation": 13148043.0, "timestamp": "2021-03-17T00:00:00+00:00", "surface_latent_heat_flux": -2243808.0, "total_water_precipitation": 0.40332, "relative_humidity": 66.767761, "surface_sensible_heat_flux": -7946054.0, "position": [43.6, 1.45], "wind_speed": 3.841429, "forecast": "2021-03-18T00:00:00+00:00", "maximum_temperature_at_2_metres": 7.787194999999997}, "geometry": {"type": "Point", "coordinates": [1.45, 43.6]}, "record_timestamp": "2021-03-17T00:00:00+00:00"}, {"datasetid": "arome-0025-sp1_sp2", "recordid": "arome_0025_sp1_sp2_sp3_lastgrib2-12966845", "fields": {"surface_net_thermal_radiation": -5365728.0, "downward_short_wave_radiation_flux": 14850977.0, "2_metre_temperature": 7.735406000000012, "dist": "0.0", "minimum_temperature_at_2_metres": 7.7432190000000105, "surface_net_solar_radiation": 13148043.0, "timestamp": "2021-03-17T00:00:00+00:00", "surface_latent_heat_flux": -2238512.0, "total_water_precipitation": 0.40332, "relative_humidity": 66.557663, "surface_sensible_heat_flux": -7911189.0, "position": [43.6, 1.45], "wind_speed": 4.464306, "forecast": "2021-03-17T23:00:00+00:00", "maximum_temperature_at_2_metres": 8.094812000000047}, "geometry": {"type": "Point", "coordinates": [1.45, 43.6]}, "record_timestamp": "2021-03-17T00:00:00+00:00"}, {"datasetid": "arome-0025-sp1_sp2", "recordid": "arome_0025_sp1_sp2_sp3_lastgrib2-12966844", "fields": {"surface_net_thermal_radiation": -5154086.0, "downward_short_wave_radiation_flux": 14850977.0, "2_metre_temperature": 8.081201000000021, "dist": "0.0", "minimum_temperature_at_2_metres": 8.075342000000035, "surface_net_solar_radiation": 13148043.0, "timestamp": "2021-03-17T00:00:00+00:00", "surface_latent_heat_flux": -2232256.0, "total_water_precipitation": 0.40332, "relative_humidity": 66.485199, "surface_sensible_heat_flux": -7885791.0, "position": [43.6, 1.45], "wind_speed": 4.553957, "forecast": "2021-03-17T22:00:00+00:00", "maximum_temperature_at_2_metres": 8.75972900000005}, "geometry": {"type": "Point", "coordinates": [1.45, 43.6]}, "record_timestamp": "2021-03-17T00:00:00+00:00"}, {"datasetid": "arome-0025-sp1_sp2", "recordid": "arome_0025_sp1_sp2_sp3_lastgrib2-12966843", "fields": {"surface_net_thermal_radiation": -4866977.0, "downward_short_wave_radiation_flux": 14850977.0, "2_metre_temperature": 8.759424000000024, "dist": "0.0", "minimum_temperature_at_2_metres": 8.731104000000016, "surface_net_solar_radiation": 13148043.0, "timestamp": "2021-03-17T00:00:00+00:00", "surface_latent_heat_flux": -2226192.0, "total_water_precipitation": 0.40332, "relative_humidity": 64.403778, "surface_sensible_heat_flux": -7881143.0, "position": [43.6, 1.45], "wind_speed": 4.793222, "forecast": "2021-03-17T21:00:00+00:00", "maximum_temperature_at_2_metres": 9.208978000000002}, "geometry": {"type": "Point", "coordinates": [1.45, 43.6]}, "record_timestamp": "2021-03-17T00:00:00+00:00"}, {"datasetid": "arome-0025-sp1_sp2", "recordid": "arome_0025_sp1_sp2_sp3_lastgrib2-12966842", "fields": {"surface_net_thermal_radiation": -4675429.0, "downward_short_wave_radiation_flux": 14850977.0, "2_metre_temperature": 9.224756000000014, "dist": "0.0", "minimum_temperature_at_2_metres": 9.226709000000028, "surface_net_solar_radiation": 13148043.0, "timestamp": "2021-03-17T00:00:00+00:00", "surface_latent_heat_flux": -2218800.0, "total_water_precipitation": 0.40332, "relative_humidity": 59.090042, "surface_sensible_heat_flux": -7821153.0, "position": [43.6, 1.45], "wind_speed": 4.675364, "forecast": "2021-03-17T20:00:00+00:00", "maximum_temperature_at_2_metres": 9.727472000000034}, "geometry": {"type": "Point", "coordinates": [1.45, 43.6]}, "record_timestamp": "2021-03-17T00:00:00+00:00"}, {"datasetid": "arome-0025-sp1_sp2", "recordid": "arome_0025_sp1_sp2_sp3_lastgrib2-12966841", "fields": {"surface_net_thermal_radiation": -4517224.0, "downward_short_wave_radiation_flux": 14850977.0, "2_metre_temperature": 9.734674000000041, "dist": "0.0", "minimum_temperature_at_2_metres": 9.735651000000018, "surface_net_solar_radiation": 13148043.0, "timestamp": "2021-03-17T00:00:00+00:00", "surface_latent_heat_flux": -2209184.0, "total_water_precipitation": 0.402344, "relative_humidity": 59.246689, "surface_sensible_heat_flux": -7738027.0, "position": [43.6, 1.45], "wind_speed": 5.252133, "forecast": "2021-03-17T19:00:00+00:00", "maximum_temperature_at_2_metres": 10.640405000000044}, "geometry": {"type": "Point", "coordinates": [1.45, 43.6]}, "record_timestamp": "2021-03-17T00:00:00+00:00"}, {"datasetid": "arome-0025-sp1_sp2", "recordid": "arome_0025_sp1_sp2_sp3_lastgrib2-12966840", "fields": {"surface_net_thermal_radiation": -4303356.0, "downward_short_wave_radiation_flux": 14850977.0, "2_metre_temperature": 10.638818000000015, "dist": "0.0", "minimum_temperature_at_2_metres": 10.642725000000041, "surface_net_solar_radiation": 13148043.0, "timestamp": "2021-03-17T00:00:00+00:00", "surface_latent_heat_flux": -2198272.0, "total_water_precipitation": 0.40332, "relative_humidity": 57.57074, "surface_sensible_heat_flux": -7661429.0, "position": [43.6, 1.45], "wind_speed": 5.781574, "forecast": "2021-03-17T18:00:00+00:00", "maximum_temperature_at_2_metres": 11.293604000000016}, "geometry": {"type": "Point", "coordinates": [1.45, 43.6]}, "record_timestamp": "2021-03-17T00:00:00+00:00"}, {"datasetid": "arome-0025-sp1_sp2", "recordid": "arome_0025_sp1_sp2_sp3_lastgrib2-12966839", "fields": {"surface_net_thermal_radiation": -4074584.0, "downward_short_wave_radiation_flux": 14726286.0, "2_metre_temperature": 11.296380999999997, "dist": "0.0", "minimum_temperature_at_2_metres": 11.295404000000019, "surface_net_solar_radiation": 13037448.0, "timestamp": "2021-03-17T00:00:00+00:00", "surface_latent_heat_flux": -2170896.0, "total_water_precipitation": 0.402344, "relative_humidity": 56.341934, "surface_sensible_heat_flux": -7452339.0, "position": [43.6, 1.45], "wind_speed": 6.205817, "forecast": "2021-03-17T17:00:00+00:00", "maximum_temperature_at_2_metres": 11.601984000000016}, "geometry": {"type": "Point", "coordinates": [1.45, 43.6]}, "record_timestamp": "2021-03-17T00:00:00+00:00"}, {"datasetid": "arome-0025-sp1_sp2", "recordid": "arome_0025_sp1_sp2_sp3_lastgrib2-12966838", "fields": {"surface_net_thermal_radiation": -3770180.0, "downward_short_wave_radiation_flux": 14192866.0, "2_metre_temperature": 11.614221000000043, "dist": "0.0", "minimum_temperature_at_2_metres": 11.617151000000035, "surface_net_solar_radiation": 12564579.0, "timestamp": "2021-03-17T00:00:00+00:00", "surface_latent_heat_flux": -2115776.0, "total_water_precipitation": 0.402344, "relative_humidity": 54.168903, "surface_sensible_heat_flux": -7058032.0, "position": [43.6, 1.45], "wind_speed": 6.11965, "forecast": "2021-03-17T16:00:00+00:00", "maximum_temperature_at_2_metres": 11.771814000000006}, "geometry": {"type": "Point", "coordinates": [1.45, 43.6]}, "record_timestamp": "2021-03-17T00:00:00+00:00"}, {"datasetid": "arome-0025-sp1_sp2", "recordid": "arome_0025_sp1_sp2_sp3_lastgrib2-12966837", "fields": {"surface_net_thermal_radiation": -3458996.0, "downward_short_wave_radiation_flux": 13291036.0, "2_metre_temperature": 11.783044000000018, "dist": "0.0", "minimum_temperature_at_2_metres": 11.784020999999996, "surface_net_solar_radiation": 11766042.0, "timestamp": "2021-03-17T00:00:00+00:00", "surface_latent_heat_flux": -2041984.0, "total_water_precipitation": 0.402832, "relative_humidity": 52.699253, "surface_sensible_heat_flux": -6446420.0, "position": [43.6, 1.45], "wind_speed": 6.27667, "forecast": "2021-03-17T15:00:00+00:00", "maximum_temperature_at_2_metres": 11.928308000000015}, "geometry": {"type": "Point", "coordinates": [1.45, 43.6]}, "record_timestamp": "2021-03-17T00:00:00+00:00"}, {"datasetid": "arome-0025-sp1_sp2", "recordid": "arome_0025_sp1_sp2_sp3_lastgrib2-12966836", "fields": {"surface_net_thermal_radiation": -3032162.0, "downward_short_wave_radiation_flux": 11765207.0, "2_metre_temperature": 11.940210000000036, "dist": "0.0", "minimum_temperature_at_2_metres": 11.87185100000005, "surface_net_solar_radiation": 10414193.0, "timestamp": "2021-03-17T00:00:00+00:00", "surface_latent_heat_flux": -1945792.0, "total_water_precipitation": 0.402832, "relative_humidity": 50.680611, "surface_sensible_heat_flux": -5561756.0, "position": [43.6, 1.45], "wind_speed": 6.33004, "forecast": "2021-03-17T14:00:00+00:00", "maximum_temperature_at_2_metres": 11.938318000000038}, "geometry": {"type": "Point", "coordinates": [1.45, 43.6]}, "record_timestamp": "2021-03-17T00:00:00+00:00"}, {"datasetid": "arome-0025-sp1_sp2", "recordid": "arome_0025_sp1_sp2_sp3_lastgrib2-12966835", "fields": {"surface_net_thermal_radiation": -2509941.0, "downward_short_wave_radiation_flux": 9581393.0, "2_metre_temperature": 11.86846300000002, "dist": "0.0", "minimum_temperature_at_2_metres": 11.609369000000015, "surface_net_solar_radiation": 8481185.0, "timestamp": "2021-03-17T00:00:00+00:00", "surface_latent_heat_flux": -1818912.0, "total_water_precipitation": 0.402832, "relative_humidity": 51.763176, "surface_sensible_heat_flux": -4437649.0, "position": [43.6, 1.45], "wind_speed": 6.195552, "forecast": "2021-03-17T13:00:00+00:00", "maximum_temperature_at_2_metres": 11.86293900000004}, "geometry": {"type": "Point", "coordinates": [1.45, 43.6]}, "record_timestamp": "2021-03-17T00:00:00+00:00"}, {"datasetid": "arome-0025-sp1_sp2", "recordid": "arome_0025_sp1_sp2_sp3_lastgrib2-12966834", "fields": {"surface_net_thermal_radiation": -1987898.0, "downward_short_wave_radiation_flux": 7239015.0, "2_metre_temperature": 11.60116000000005, "dist": "0.0", "minimum_temperature_at_2_metres": 11.103632000000005, "surface_net_solar_radiation": 6406432.0, "timestamp": "2021-03-17T00:00:00+00:00", "surface_latent_heat_flux": -1630947.0, "total_water_precipitation": 0.402832, "relative_humidity": 54.006516, "surface_sensible_heat_flux": -3317529.0, "position": [43.6, 1.45], "wind_speed": 5.954789, "forecast": "2021-03-17T12:00:00+00:00", "maximum_temperature_at_2_metres": 11.595087000000035}, "geometry": {"type": "Point", "coordinates": [1.45, 43.6]}, "record_timestamp": "2021-03-17T00:00:00+00:00"}, {"datasetid": "arome-0025-sp1_sp2", "recordid": "arome_0025_sp1_sp2_sp3_lastgrib2-12966833", "fields": {"surface_net_thermal_radiation": -1478904.0, "downward_short_wave_radiation_flux": 4871715.0, "2_metre_temperature": 11.118799000000024, "dist": "0.0", "minimum_temperature_at_2_metres": 10.948999000000015, "surface_net_solar_radiation": 4309261.5, "timestamp": "2021-03-17T00:00:00+00:00", "surface_latent_heat_flux": -1369730.0, "total_water_precipitation": 0.402832, "relative_humidity": 54.900833, "surface_sensible_heat_flux": -2264471.0, "position": [43.6, 1.45], "wind_speed": 6.747961, "forecast": "2021-03-17T11:00:00+00:00", "maximum_temperature_at_2_metres": 11.110986000000025}, "geometry": {"type": "Point", "coordinates": [1.45, 43.6]}, "record_timestamp": "2021-03-17T00:00:00+00:00"}, {"datasetid": "arome-0025-sp1_sp2", "recordid": "arome_0025_sp1_sp2_sp3_lastgrib2-12966832", "fields": {"surface_net_thermal_radiation": -1056889.0, "downward_short_wave_radiation_flux": 2830028.75, "2_metre_temperature": 10.946466000000044, "dist": "0.0", "minimum_temperature_at_2_metres": 10.43740200000002, "surface_net_solar_radiation": 2503804.5, "timestamp": "2021-03-17T00:00:00+00:00", "surface_latent_heat_flux": -991512.0, "total_water_precipitation": 0.402832, "relative_humidity": 63.348633, "surface_sensible_heat_flux": -1432433.0, "position": [43.6, 1.45], "wind_speed": 6.875549, "forecast": "2021-03-17T10:00:00+00:00", "maximum_temperature_at_2_metres": 10.946466000000044}, "geometry": {"type": "Point", "coordinates": [1.45, 43.6]}, "record_timestamp": "2021-03-17T00:00:00+00:00"}, {"datasetid": "arome-0025-sp1_sp2", "recordid": "arome_0025_sp1_sp2_sp3_lastgrib2-12966831", "fields": {"surface_net_thermal_radiation": -720898.0, "downward_short_wave_radiation_flux": 1241571.625, "2_metre_temperature": 10.41329300000001, "dist": "0.0", "minimum_temperature_at_2_metres": 9.978967000000011, "surface_net_solar_radiation": 1098493.75, "timestamp": "2021-03-17T00:00:00+00:00", "surface_latent_heat_flux": -607543.0, "total_water_precipitation": 0.402832, "relative_humidity": 73.629745, "surface_sensible_heat_flux": -876639.0, "position": [43.6, 1.45], "wind_speed": 5.90029, "forecast": "2021-03-17T09:00:00+00:00", "maximum_temperature_at_2_metres": 10.418176000000017}, "geometry": {"type": "Point", "coordinates": [1.45, 43.6]}, "record_timestamp": "2021-03-17T00:00:00+00:00"}, {"datasetid": "arome-0025-sp1_sp2", "recordid": "arome_0025_sp1_sp2_sp3_lastgrib2-12966830", "fields": {"surface_net_thermal_radiation": -511116.0, "downward_short_wave_radiation_flux": 327860.25, "2_metre_temperature": 9.934564000000023, "dist": "0.0", "minimum_temperature_at_2_metres": 9.530542000000025, "surface_net_solar_radiation": 290054.46875, "timestamp": "2021-03-17T00:00:00+00:00", "surface_latent_heat_flux": -335967.0, "total_water_precipitation": 0.402832, "relative_humidity": 82.603119, "surface_sensible_heat_flux": -572960.0, "position": [43.6, 1.45], "wind_speed": 5.780795, "forecast": "2021-03-17T08:00:00+00:00", "maximum_temperature_at_2_metres": 9.928705000000036}, "geometry": {"type": "Point", "coordinates": [1.45, 43.6]}, "record_timestamp": "2021-03-17T00:00:00+00:00"}, {"datasetid": "arome-0025-sp1_sp2", "recordid": "arome_0025_sp1_sp2_sp3_lastgrib2-12966829", "fields": {"surface_net_thermal_radiation": -446532.0, "downward_short_wave_radiation_flux": 42511.359375, "2_metre_temperature": 9.539819000000023, "dist": "0.0", "minimum_temperature_at_2_metres": 9.171807999999999, "surface_net_solar_radiation": 37659.203125, "timestamp": "2021-03-17T00:00:00+00:00", "surface_latent_heat_flux": -194381.0, "total_water_precipitation": 0.377441, "relative_humidity": 86.225037, "surface_sensible_heat_flux": -431973.0, "position": [43.6, 1.45], "wind_speed": 4.78359, "forecast": "2021-03-17T07:00:00+00:00", "maximum_temperature_at_2_metres": 9.711694000000023}, "geometry": {"type": "Point", "coordinates": [1.45, 43.6]}, "record_timestamp": "2021-03-17T00:00:00+00:00"}, {"datasetid": "arome-0025-sp1_sp2", "recordid": "arome_0025_sp1_sp2_sp3_lastgrib2-12966828", "fields": {"surface_net_thermal_radiation": -340002.0, "downward_short_wave_radiation_flux": 0.0, "2_metre_temperature": 9.202539000000002, "dist": "0.0", "minimum_temperature_at_2_metres": 9.188654000000042, "surface_net_solar_radiation": 0.0, "timestamp": "2021-03-17T00:00:00+00:00", "surface_latent_heat_flux": -157196.0, "total_water_precipitation": 0.190186, "relative_humidity": 88.459595, "surface_sensible_heat_flux": -362208.0, "position": [43.6, 1.45], "wind_speed": 4.105865, "forecast": "2021-03-17T06:00:00+00:00", "maximum_temperature_at_2_metres": 9.532678000000033}, "geometry": {"type": "Point", "coordinates": [1.45, 43.6]}, "record_timestamp": "2021-03-17T00:00:00+00:00"}, {"datasetid": "arome-0025-sp1_sp2", "recordid": "arome_0025_sp1_sp2_sp3_lastgrib2-12966827", "fields": {"surface_net_thermal_radiation": -177369.0, "downward_short_wave_radiation_flux": 0.0, "2_metre_temperature": 9.30089700000002, "dist": "0.0", "minimum_temperature_at_2_metres": 9.288202000000013, "surface_net_solar_radiation": 0.0, "timestamp": "2021-03-17T00:00:00+00:00", "surface_latent_heat_flux": -151853.0, "total_water_precipitation": 0.189941, "relative_humidity": 92.14817, "surface_sensible_heat_flux": -353125.0, "position": [43.6, 1.45], "wind_speed": 3.637204, "forecast": "2021-03-17T05:00:00+00:00", "maximum_temperature_at_2_metres": 9.726251000000047}, "geometry": {"type": "Point", "coordinates": [1.45, 43.6]}, "record_timestamp": "2021-03-17T00:00:00+00:00"}, {"datasetid": "arome-0025-sp1_sp2", "recordid": "arome_0025_sp1_sp2_sp3_lastgrib2-12966826", "fields": {"surface_net_thermal_radiation": -133954.0, "downward_short_wave_radiation_flux": 0.0, "2_metre_temperature": 9.398859000000016, "dist": "0.0", "minimum_temperature_at_2_metres": 9.227350000000001, "surface_net_solar_radiation": 0.0, "timestamp": "2021-03-17T00:00:00+00:00", "surface_latent_heat_flux": -106560.0, "total_water_precipitation": 0.163086, "relative_humidity": 91.344414, "surface_sensible_heat_flux": -299994.0, "position": [43.6, 1.45], "wind_speed": 4.776591, "forecast": "2021-03-17T04:00:00+00:00", "maximum_temperature_at_2_metres": 9.43340500000005}, "geometry": {"type": "Point", "coordinates": [1.45, 43.6]}, "record_timestamp": "2021-03-17T00:00:00+00:00"}, {"datasetid": "arome-0025-sp1_sp2", "recordid": "arome_0025_sp1_sp2_sp3_lastgrib2-12966825", "fields": {"surface_net_thermal_radiation": -106375.0, "downward_short_wave_radiation_flux": 0.0, "2_metre_temperature": 9.429468000000043, "dist": "0.0", "minimum_temperature_at_2_metres": 9.425806000000023, "surface_net_solar_radiation": 0.0, "timestamp": "2021-03-17T00:00:00+00:00", "surface_latent_heat_flux": -81326.0, "total_water_precipitation": 0.064453, "relative_humidity": 90.455215, "surface_sensible_heat_flux": -215354.0, "position": [43.6, 1.45], "wind_speed": 4.340807, "forecast": "2021-03-17T03:00:00+00:00", "maximum_temperature_at_2_metres": 9.973352000000034}, "geometry": {"type": "Point", "coordinates": [1.45, 43.6]}, "record_timestamp": "2021-03-17T00:00:00+00:00"}, {"datasetid": "arome-0025-sp1_sp2", "recordid": "arome_0025_sp1_sp2_sp3_lastgrib2-12966824", "fields": {"surface_net_thermal_radiation": -72446.0, "downward_short_wave_radiation_flux": 0.0, "2_metre_temperature": 9.963617, "dist": "0.0", "minimum_temperature_at_2_metres": 9.975153000000034, "surface_net_solar_radiation": 0.0, "timestamp": "2021-03-17T00:00:00+00:00", "surface_latent_heat_flux": -47529.0, "total_water_precipitation": 0.027832, "relative_humidity": 87.669182, "surface_sensible_heat_flux": -132275.1875, "position": [43.6, 1.45], "wind_speed": 5.02856, "forecast": "2021-03-17T02:00:00+00:00", "maximum_temperature_at_2_metres": 10.482690000000048}, "geometry": {"type": "Point", "coordinates": [1.45, 43.6]}, "record_timestamp": "2021-03-17T00:00:00+00:00"}, {"datasetid": "arome-0025-sp1_sp2", "recordid": "arome_0025_sp1_sp2_sp3_lastgrib2-12966823", "fields": {"surface_net_thermal_radiation": -38864.875, "downward_short_wave_radiation_flux": 0.0, "2_metre_temperature": 10.52440800000005, "dist": "0.0", "minimum_temperature_at_2_metres": 10.526147000000037, "surface_net_solar_radiation": 0.0, "timestamp": "2021-03-17T00:00:00+00:00", "surface_latent_heat_flux": -19824.0, "total_water_precipitation": 0.0, "relative_humidity": 86.249657, "surface_sensible_heat_flux": -55633.5625, "position": [43.6, 1.45], "wind_speed": 5.15487, "forecast": "2021-03-17T01:00:00+00:00", "maximum_temperature_at_2_metres": 10.964319000000046}, "geometry": {"type": "Point", "coordinates": [1.45, 43.6]}, "record_timestamp": "2021-03-17T00:00:00+00:00"}, {"datasetid": "arome-0025-sp1_sp2", "recordid": "arome_0025_sp1_sp2_sp3_lastgrib2-12966822", "fields": {"wind_speed": 3.732625, "2_metre_temperature": 10.795343000000003, "dist": "0.0", "timestamp": "2021-03-17T00:00:00+00:00", "forecast": "2021-03-17T00:00:00+00:00", "relative_humidity": 80.273483, "position": [43.6, 1.45]}, "geometry": {"type": "Point", "coordinates": [1.45, 43.6]}, "record_timestamp": "2021-03-17T00:00:00+00:00"}]}