{"nhits": 43, "parameters": {"dataset": ["arome-0025-sp1_sp2"], "timezone": "UTC", "rows": 100, "start": 0, "sort": ["forecast"], "format": "json", "geofilter.distance": ["43.60, 1.45, 100"]}, "records": [{"datasetid": "arome-0025-sp1_sp2", "recordid": "arome_0025_sp1_sp2_sp3_lastgrib2-12966864", "fields": {"surface_net_thermal_radiation": -18934192.0, "downward_short_wave_radiation_flux": 44524636.0, "2_metre_temperature": 20.801904000000036, "dist": "0.0", "minimum_temperature_at_2_metres": 20.800928, "surface_net_solar_radiation": 39427708.0, "timestamp": "2021-04-01T00:00:00+00:00", "surface_latent_heat_flux": -2483456.0, "total_water_precipitation": 0.0, "relative_humidity": 46.830811, "surface_sensible_heat_flux": -18035552.0, "position": [43.6, 1.45], "wind_speed": 2.35134, "forecast": "2021-04-02T18:00:00+00:00", "maximum_temperature_at_2_metres": 21.73281300000002}, "geometry": {"type": "Point", "coordinates": [1.45, 43.6]}, "record_timestamp": "2021-04-01T00:00:00+00:00"}, {"datasetid": "arome-0025-sp1_sp2", "recordid": "arome_0025_sp1_sp2_sp3_lastgrib2-12966863", "fields": {"surface_net_thermal_radiation": -18589088.0, "downward_short_wave_radiation_flux": 44228464.0, "2_metre_temperature": 21.751123000000007, "dist": "0.0", "minimum_temperature_at_2_metres": 21.75698200000005, "surface_net_solar_radiation": 39166248.0, "timestamp": "2021-04-01T00:00:00+00:00", "surface_latent_heat_flux": -2450464.0, "total_water_precipitation": 0.0, "relative_humidity": 44.181343, "surface_sensible_heat_flux": -17801136.0, "position": [43.6, 1.45], "wind_speed": 2.063181, "forecast": "2021-04-02T17:00:00+00:00", "maximum_temperature_at_2_metres": 22.402246000000048}, "geometry": {"type": "Point", "coordinates": [1.45, 43.6]}, "record_timestamp": "2021-04-01T00:00:00+00:00"}, {"datasetid": "arome-0025-sp1_sp2", "recordid": "arome_0025_sp1_sp2_sp3_lastgrib2-12966862", "fields": {"surface_net_thermal_radiation": -18138912.0, "downward_short_wave_radiation_flux": 43418600.0, "2_metre_temperature": 22.404199000000006, "dist": "0.0", "minimum_temperature_at_2_metres": 22.349512000000004, "surface_net_solar_radiation": 38448224.0, "timestamp": "2021-04-01T00:00:00+00:00", "surface_latent_heat_flux": -2378400.0, "total_water_precipitation": 0.0, "relative_humidity": 43.193333, "surface_sensible_heat_flux": -17426848.0, "position": [43.6, 1.45], "wind_speed": 0.171451, "forecast": "2021-04-02T16:00:00+00:00", "maximum_temperature_at_2_metres": 22.64272500000004}, "geometry": {"type": "Point", "coordinates": [1.45, 43.6]}, "record_timestamp": "2021-04-01T00:00:00+00:00"}, {"datasetid": "arome-0025-sp1_sp2", "recordid": "arome_0025_sp1_sp2_sp3_lastgrib2-12966861", "fields": {"surface_net_thermal_radiation": -17566592.0, "downward_short_wave_radiation_flux": 41973356.0, "2_metre_temperature": 22.69960900000001, "dist": "0.0", "minimum_temperature_at_2_metres": 22.49843800000002, "surface_net_solar_radiation": 37167724.0, "timestamp": "2021-04-01T00:00:00+00:00", "surface_latent_heat_flux": -2266416.0, "total_water_precipitation": 0.0, "relative_humidity": 42.673477, "surface_sensible_heat_flux": -16833104.0, "position": [43.6, 1.45], "wind_speed": 1.829107, "forecast": "2021-04-02T15:00:00+00:00", "maximum_temperature_at_2_metres": 22.70156300000002}, "geometry": {"type": "Point", "coordinates": [1.45, 43.6]}, "record_timestamp": "2021-04-01T00:00:00+00:00"}, {"datasetid": "arome-0025-sp1_sp2", "recordid": "arome_0025_sp1_sp2_sp3_lastgrib2-12966860", "fields": {"surface_net_thermal_radiation": -16834192.0, "downward_short_wave_radiation_flux": 39708784.0, "2_metre_temperature": 22.47573200000005, "dist": "0.0", "minimum_temperature_at_2_metres": 21.466943000000015, "surface_net_solar_radiation": 35164372.0, "timestamp": "2021-04-01T00:00:00+00:00", "surface_latent_heat_flux": -2115152.0, "total_water_precipitation": 0.0, "relative_humidity": 46.680008, "surface_sensible_heat_flux": -15983904.0, "position": [43.6, 1.45], "wind_speed": 1.531101, "forecast": "2021-04-02T14:00:00+00:00", "maximum_temperature_at_2_metres": 22.476953000000037}, "geometry": {"type": "Point", "coordinates": [1.45, 43.6]}, "record_timestamp": "2021-04-01T00:00:00+00:00"}, {"datasetid": "arome-0025-sp1_sp2", "recordid": "arome_0025_sp1_sp2_sp3_lastgrib2-12966859", "fields": {"surface_net_thermal_radiation": -16019856.0, "downward_short_wave_radiation_flux": 36990600.0, "2_metre_temperature": 21.490137000000004, "dist": "0.0", "minimum_temperature_at_2_metres": 20.266748000000007, "surface_net_solar_radiation": 32752724.0, "timestamp": "2021-04-01T00:00:00+00:00", "surface_latent_heat_flux": -1953312.0, "total_water_precipitation": 0.0, "relative_humidity": 48.163681, "surface_sensible_heat_flux": -15013296.0, "position": [43.6, 1.45], "wind_speed": 1.897644, "forecast": "2021-04-02T13:00:00+00:00", "maximum_temperature_at_2_metres": 21.495996000000048}, "geometry": {"type": "Point", "coordinates": [1.45, 43.6]}, "record_timestamp": "2021-04-01T00:00:00+00:00"}, {"datasetid": "arome-0025-sp1_sp2", "recordid": "arome_0025_sp1_sp2_sp3_lastgrib2-12966858", "fields": {"surface_net_thermal_radiation": -15197136.0, "downward_short_wave_radiation_flux": 34036152.0, "2_metre_temperature": 20.252832000000012, "dist": "0.0", "minimum_temperature_at_2_metres": 18.665918000000033, "surface_net_solar_radiation": 30126862.0, "timestamp": "2021-04-01T00:00:00+00:00", "surface_latent_heat_flux": -1787648.0, "total_water_precipitation": 0.0, "relative_humidity": 50.191185, "surface_sensible_heat_flux": -13939168.0, "position": [43.6, 1.45], "wind_speed": 2.147357, "forecast": "2021-04-02T12:00:00+00:00", "maximum_temperature_at_2_metres": 20.26064500000001}, "geometry": {"type": "Point", "coordinates": [1.45, 43.6]}, "record_timestamp": "2021-04-01T00:00:00+00:00"}, {"datasetid": "arome-0025-sp1_sp2", "recordid": "arome_0025_sp1_sp2_sp3_lastgrib2-12966857", "fields": {"surface_net_thermal_radiation": -14397762.0, "downward_short_wave_radiation_flux": 31063552.0, "2_metre_temperature": 18.638329999999996, "dist": "0.0", "minimum_temperature_at_2_metres": 16.863184000000047, "surface_net_solar_radiation": 27485836.0, "timestamp": "2021-04-01T00:00:00+00:00", "surface_latent_heat_flux": -1632672.0, "total_water_precipitation": 0.0, "relative_humidity": 53.966465, "surface_sensible_heat_flux": -12890560.0, "position": [43.6, 1.45], "wind_speed": 2.380641, "forecast": "2021-04-02T11:00:00+00:00", "maximum_temperature_at_2_metres": 18.627588000000003}, "geometry": {"type": "Point", "coordinates": [1.45, 43.6]}, "record_timestamp": "2021-04-01T00:00:00+00:00"}, {"datasetid": "arome-0025-sp1_sp2", "recordid": "arome_0025_sp1_sp2_sp3_lastgrib2-12966856", "fields": {"surface_net_thermal_radiation": -13672523.0, "downward_short_wave_radiation_flux": 28295224.0, "2_metre_temperature": 16.850977, "dist": "0.0", "minimum_temperature_at_2_metres": 14.912256000000014, "surface_net_solar_radiation": 25030002.0, "timestamp": "2021-04-01T00:00:00+00:00", "surface_latent_heat_flux": -1503456.0, "total_water_precipitation": 0.0, "relative_humidity": 59.90155, "surface_sensible_heat_flux": -11943200.0, "position": [43.6, 1.45], "wind_speed": 2.89309, "forecast": "2021-04-02T10:00:00+00:00", "maximum_temperature_at_2_metres": 16.85585900000001}, "geometry": {"type": "Point", "coordinates": [1.45, 43.6]}, "record_timestamp": "2021-04-01T00:00:00+00:00"}, {"datasetid": "arome-0025-sp1_sp2", "recordid": "arome_0025_sp1_sp2_sp3_lastgrib2-12966855", "fields": {"surface_net_thermal_radiation": -13053403.0, "downward_short_wave_radiation_flux": 25928666.0, "2_metre_temperature": 14.844141000000036, "dist": "0.0", "minimum_temperature_at_2_metres": 12.83168900000004, "surface_net_solar_radiation": 22938930.0, "timestamp": "2021-04-01T00:00:00+00:00", "surface_latent_heat_flux": -1407056.0, "total_water_precipitation": 0.0, "relative_humidity": 69.628082, "surface_sensible_heat_flux": -11154366.0, "position": [43.6, 1.45], "wind_speed": 3.232604, "forecast": "2021-04-02T09:00:00+00:00", "maximum_temperature_at_2_metres": 14.84707000000003}, "geometry": {"type": "Point", "coordinates": [1.45, 43.6]}, "record_timestamp": "2021-04-01T00:00:00+00:00"}, {"datasetid": "arome-0025-sp1_sp2", "recordid": "arome_0025_sp1_sp2_sp3_lastgrib2-12966854", "fields": {"surface_net_thermal_radiation": -12557666.0, "downward_short_wave_radiation_flux": 24126562.0, "2_metre_temperature": 12.79335900000001, "dist": "0.0", "minimum_temperature_at_2_metres": 11.106348000000025, "surface_net_solar_radiation": 21352476.0, "timestamp": "2021-04-01T00:00:00+00:00", "surface_latent_heat_flux": -1292912.0, "total_water_precipitation": 0.0, "relative_humidity": 76.487686, "surface_sensible_heat_flux": -10605097.0, "position": [43.6, 1.45], "wind_speed": 3.427587, "forecast": "2021-04-02T08:00:00+00:00", "maximum_temperature_at_2_metres": 12.785547000000008}, "geometry": {"type": "Point", "coordinates": [1.45, 43.6]}, "record_timestamp": "2021-04-01T00:00:00+00:00"}, {"datasetid": "arome-0025-sp1_sp2", "recordid": "arome_0025_sp1_sp2_sp3_lastgrib2-12966853", "fields": {"surface_net_thermal_radiation": -12163424.0, "downward_short_wave_radiation_flux": 22993624.0, "2_metre_temperature": 11.06118200000003, "dist": "0.0", "minimum_temperature_at_2_metres": 10.100000000000023, "surface_net_solar_radiation": 20358376.0, "timestamp": "2021-04-01T00:00:00+00:00", "surface_latent_heat_flux": -1201264.0, "total_water_precipitation": 0.0, "relative_humidity": 82.079193, "surface_sensible_heat_flux": -10286521.0, "position": [43.6, 1.45], "wind_speed": 3.4348, "forecast": "2021-04-02T07:00:00+00:00", "maximum_temperature_at_2_metres": 11.06118200000003}, "geometry": {"type": "Point", "coordinates": [1.45, 43.6]}, "record_timestamp": "2021-04-01T00:00:00+00:00"}, {"datasetid": "arome-0025-sp1_sp2", "recordid": "arome_0025_sp1_sp2_sp3_lastgrib2-12966852", "fields": {"surface_net_thermal_radiation": -11848183.0, "downward_short_wave_radiation_flux": 22544300.0, "2_metre_temperature": 10.085657000000026, "dist": "0.0", "minimum_temperature_at_2_metres": 9.848505000000046, "surface_net_solar_radiation": 19965568.0, "timestamp": "2021-04-01T00:00:00+00:00", "surface_latent_heat_flux": -1178640.0, "total_water_precipitation": 0.0, "relative_humidity": 87.860352, "surface_sensible_heat_flux": -10150928.0, "position": [43.6, 1.45], "wind_speed": 3.25276, "forecast": "2021-04-02T06:00:00+00:00", "maximum_temperature_at_2_metres": 10.084680000000048}, "geometry": {"type": "Point", "coordinates": [1.45, 43.6]}, "record_timestamp": "2021-04-01T00:00:00+00:00"}, {"datasetid": "arome-0025-sp1_sp2", "recordid": "arome_0025_sp1_sp2_sp3_lastgrib2-12966851", "fields": {"surface_net_thermal_radiation": -11563891.0, "downward_short_wave_radiation_flux": 22520050.0, "2_metre_temperature": 9.840051000000017, "dist": "0.0", "minimum_temperature_at_2_metres": 9.52907700000003, "surface_net_solar_radiation": 19944056.0, "timestamp": "2021-04-01T00:00:00+00:00", "surface_latent_heat_flux": -1212592.0, "total_water_precipitation": 0.0, "relative_humidity": 89.23967, "surface_sensible_heat_flux": -10149989.0, "position": [43.6, 1.45], "wind_speed": 3.435709, "forecast": "2021-04-02T05:00:00+00:00", "maximum_temperature_at_2_metres": 9.83379500000001}, "geometry": {"type": "Point", "coordinates": [1.45, 43.6]}, "record_timestamp": "2021-04-01T00:00:00+00:00"}, {"datasetid": "arome-0025-sp1_sp2", "recordid": "arome_0025_sp1_sp2_sp3_lastgrib2-12966850", "fields": {"surface_net_thermal_radiation": -11281004.0, "downward_short_wave_radiation_flux": 22520032.0, "2_metre_temperature": 9.508997000000022, "dist": "0.0", "minimum_temperature_at_2_metres": 9.498559999999998, "surface_net_solar_radiation": 19944104.0, "timestamp": "2021-04-01T00:00:00+00:00", "surface_latent_heat_flux": -1249280.0, "total_water_precipitation": 0.0, "relative_humidity": 88.566467, "surface_sensible_heat_flux": -10139517.0, "position": [43.6, 1.45], "wind_speed": 3.160373, "forecast": "2021-04-02T04:00:00+00:00", "maximum_temperature_at_2_metres": 9.703333000000043}, "geometry": {"type": "Point", "coordinates": [1.45, 43.6]}, "record_timestamp": "2021-04-01T00:00:00+00:00"}, {"datasetid": "arome-0025-sp1_sp2", "recordid": "arome_0025_sp1_sp2_sp3_lastgrib2-12966849", "fields": {"surface_net_thermal_radiation": -10989792.0, "downward_short_wave_radiation_flux": 22520032.0, "2_metre_temperature": 9.691370000000006, "dist": "0.0", "minimum_temperature_at_2_metres": 9.701440000000048, "surface_net_solar_radiation": 19944104.0, "timestamp": "2021-04-01T00:00:00+00:00", "surface_latent_heat_flux": -1279140.0, "total_water_precipitation": 0.0, "relative_humidity": 84.566536, "surface_sensible_heat_flux": -10114197.0, "position": [43.6, 1.45], "wind_speed": 2.84517, "forecast": "2021-04-02T03:00:00+00:00", "maximum_temperature_at_2_metres": 10.190393000000029}, "geometry": {"type": "Point", "coordinates": [1.45, 43.6]}, "record_timestamp": "2021-04-01T00:00:00+00:00"}, {"datasetid": "arome-0025-sp1_sp2", "recordid": "arome_0025_sp1_sp2_sp3_lastgrib2-12966848", "fields": {"surface_net_thermal_radiation": -10690059.0, "downward_short_wave_radiation_flux": 22520032.0, "2_metre_temperature": 10.18346600000001, "dist": "0.0", "minimum_temperature_at_2_metres": 10.189324999999997, "surface_net_solar_radiation": 19944104.0, "timestamp": "2021-04-01T00:00:00+00:00", "surface_latent_heat_flux": -1301781.0, "total_water_precipitation": 0.0, "relative_humidity": 81.59726, "surface_sensible_heat_flux": -10079981.0, "position": [43.6, 1.45], "wind_speed": 2.664662, "forecast": "2021-04-02T02:00:00+00:00", "maximum_temperature_at_2_metres": 10.39187000000004}, "geometry": {"type": "Point", "coordinates": [1.45, 43.6]}, "record_timestamp": "2021-04-01T00:00:00+00:00"}, {"datasetid": "arome-0025-sp1_sp2", "recordid": "arome_0025_sp1_sp2_sp3_lastgrib2-12966847", "fields": {"surface_net_thermal_radiation": -10435155.0, "downward_short_wave_radiation_flux": 22520032.0, "2_metre_temperature": 10.39425, "dist": "0.0", "minimum_temperature_at_2_metres": 10.391321000000005, "surface_net_solar_radiation": 19944104.0, "timestamp": "2021-04-01T00:00:00+00:00", "surface_latent_heat_flux": -1313558.0, "total_water_precipitation": 0.0, "relative_humidity": 82.3228, "surface_sensible_heat_flux": -10023580.0, "position": [43.6, 1.45], "wind_speed": 2.878807, "forecast": "2021-04-02T01:00:00+00:00", "maximum_temperature_at_2_metres": 11.037500000000023}, "geometry": {"type": "Point", "coordinates": [1.45, 43.6]}, "record_timestamp": "2021-04-01T00:00:00+00:00"}, {"datasetid": "arome-0025-sp1_sp2", "recordid": "arome_0025_sp1_sp2_sp3_lastgrib2-12966846", "fields": {"surface_net_thermal_radiation": -10192724.0, "downward_short_wave_radiation_flux": 22520032.0, "2_metre_temperature": 11.039086999999995, "dist": "0.0", "minimum_temperature_at_2_metres": 11.044946000000039, "surface_net_solar_radiation": 19944104.0, "timestamp": "2021-04-01T00:00:00+00:00", "surface_latent_heat_flux": -1320453.0, "total_water_precipitation": 0.0, "relative_humidity": 80.087166, "surface_sensible_heat_flux": -9945373.0, "position": [43.6, 1.45], "wind_speed": 3.564066, "forecast": "2021-04-02T00:00:00+00:00", "maximum_temperature_at_2_metres": 11.778223000000025}, "geometry": {"type": "Point", "coordinates": [1.45, 43.6]}, "record_timestamp": "2021-04-01T00:00:00+00:00"}, {"datasetid": "arome-0025-sp1_sp2", "recordid": "arome_0025_sp1_sp2_sp3_lastgrib2-12966845", "fields": {"surface_net_thermal_radiation": -9950635.0, "downward_short_wave_radiation_flux": 22520032.0, "2_metre_temperature": 11.783289000000025, "dist": "0.0", "minimum_temperature_at_2_metres": 11.791101000000026, "surface_net_solar_radiation": 19944104.0, "timestamp": "2021-04-01T00:00:00+00:00", "surface_latent_heat_flux": -1322981.0, "total_water_precipitation": 0.0, "relative_humidity": 76.388458, "surface_sensible_heat_flux": -9875108.0, "position": [43.6, 1.45], "wind_speed": 2.799655, "forecast": "2021-04-01T23:00:00+00:00", "maximum_temperature_at_2_metres": 12.575983000000008}, "geometry": {"type": "Point", "coordinates": [1.45, 43.6]}, "record_timestamp": "2021-04-01T00:00:00+00:00"}, {"datasetid": "arome-0025-sp1_sp2", "recordid": "arome_0025_sp1_sp2_sp3_lastgrib2-12966844", "fields": {"surface_net_thermal_radiation": -9651636.0, "downward_short_wave_radiation_flux": 22520032.0, "2_metre_temperature": 12.566370000000006, "dist": "0.0", "minimum_temperature_at_2_metres": 12.565515000000005, "surface_net_solar_radiation": 19944104.0, "timestamp": "2021-04-01T00:00:00+00:00", "surface_latent_heat_flux": -1331005.0, "total_water_precipitation": 0.0, "relative_humidity": 72.410446, "surface_sensible_heat_flux": -9820132.0, "position": [43.6, 1.45], "wind_speed": 3.242906, "forecast": "2021-04-01T22:00:00+00:00", "maximum_temperature_at_2_metres": 13.630914000000018}, "geometry": {"type": "Point", "coordinates": [1.45, 43.6]}, "record_timestamp": "2021-04-01T00:00:00+00:00"}, {"datasetid": "arome-0025-sp1_sp2", "recordid": "arome_0025_sp1_sp2_sp3_lastgrib2-12966843", "fields": {"surface_net_thermal_radiation": -9341494.0, "downward_short_wave_radiation_flux": 22520032.0, "2_metre_temperature": 13.627679, "dist": "0.0", "minimum_temperature_at_2_metres": 13.628625, "surface_net_solar_radiation": 19944104.0, "timestamp": "2021-04-01T00:00:00+00:00", "surface_latent_heat_flux": -1331367.0, "total_water_precipitation": 0.0, "relative_humidity": 63.48597, "surface_sensible_heat_flux": -9761885.0, "position": [43.6, 1.45], "wind_speed": 3.746335, "forecast": "2021-04-01T21:00:00+00:00", "maximum_temperature_at_2_metres": 14.818262000000004}, "geometry": {"type": "Point", "coordinates": [1.45, 43.6]}, "record_timestamp": "2021-04-01T00:00:00+00:00"}, {"datasetid": "arome-0025-sp1_sp2", "recordid": "arome_0025_sp1_sp2_sp3_lastgrib2-12966842", "fields": {"surface_net_thermal_radiation": -9044030.0, "downward_short_wave_radiation_flux": 22520032.0, "2_metre_temperature": 14.849512000000004, "dist": "0.0", "minimum_temperature_at_2_metres": 14.848535000000027, "surface_net_solar_radiation": 19944104.0, "timestamp": "2021-04-01T00:00:00+00:00", "surface_latent_heat_flux": -1330786.0, "total_water_precipitation": 0.0, "relative_humidity": 53.095505, "surface_sensible_heat_flux": -9696805.0, "position": [43.6, 1.45], "wind_speed": 3.894573, "forecast": "2021-04-01T20:00:00+00:00", "maximum_temperature_at_2_metres": 15.800927999999999}, "geometry": {"type": "Point", "coordinates": [1.45, 43.6]}, "record_timestamp": "2021-04-01T00:00:00+00:00"}, {"datasetid": "arome-0025-sp1_sp2", "recordid": "arome_0025_sp1_sp2_sp3_lastgrib2-12966841", "fields": {"surface_net_thermal_radiation": -8720258.0, "downward_short_wave_radiation_flux": 22520032.0, "2_metre_temperature": 15.840479000000016, "dist": "0.0", "minimum_temperature_at_2_metres": 15.84340800000001, "surface_net_solar_radiation": 19944104.0, "timestamp": "2021-04-01T00:00:00+00:00", "surface_latent_heat_flux": -1329753.0, "total_water_precipitation": 0.0, "relative_humidity": 48.316895, "surface_sensible_heat_flux": -9634623.0, "position": [43.6, 1.45], "wind_speed": 4.494639, "forecast": "2021-04-01T19:00:00+00:00", "maximum_temperature_at_2_metres": 17.351709000000028}, "geometry": {"type": "Point", "coordinates": [1.45, 43.6]}, "record_timestamp": "2021-04-01T00:00:00+00:00"}, {"datasetid": "arome-0025-sp1_sp2", "recordid": "arome_0025_sp1_sp2_sp3_lastgrib2-12966840", "fields": {"surface_net_thermal_radiation": -8361675.0, "downward_short_wave_radiation_flux": 22507620.0, "2_metre_temperature": 17.388818000000015, "dist": "0.0", "minimum_temperature_at_2_metres": 17.396631000000014, "surface_net_solar_radiation": 19932840.0, "timestamp": "2021-04-01T00:00:00+00:00", "surface_latent_heat_flux": -1326545.0, "total_water_precipitation": 0.0, "relative_humidity": 46.312805, "surface_sensible_heat_flux": -9547881.0, "position": [43.6, 1.45], "wind_speed": 4.481845, "forecast": "2021-04-01T18:00:00+00:00", "maximum_temperature_at_2_metres": 19.35927700000002}, "geometry": {"type": "Point", "coordinates": [1.45, 43.6]}, "record_timestamp": "2021-04-01T00:00:00+00:00"}, {"datasetid": "arome-0025-sp1_sp2", "recordid": "arome_0025_sp1_sp2_sp3_lastgrib2-12966839", "fields": {"surface_net_thermal_radiation": -7935475.0, "downward_short_wave_radiation_flux": 22120164.0, "2_metre_temperature": 19.379053, "dist": "0.0", "minimum_temperature_at_2_metres": 19.368311000000006, "surface_net_solar_radiation": 19590528.0, "timestamp": "2021-04-01T00:00:00+00:00", "surface_latent_heat_flux": -1275688.0, "total_water_precipitation": 0.0, "relative_humidity": 42.393829, "surface_sensible_heat_flux": -9265193.0, "position": [43.6, 1.45], "wind_speed": 4.549948, "forecast": "2021-04-01T17:00:00+00:00", "maximum_temperature_at_2_metres": 20.39760700000005}, "geometry": {"type": "Point", "coordinates": [1.45, 43.6]}, "record_timestamp": "2021-04-01T00:00:00+00:00"}, {"datasetid": "arome-0025-sp1_sp2", "recordid": "arome_0025_sp1_sp2_sp3_lastgrib2-12966838", "fields": {"surface_net_thermal_radiation": -7422010.0, "downward_short_wave_radiation_flux": 21080972.0, "2_metre_temperature": 20.422266000000036, "dist": "0.0", "minimum_temperature_at_2_metres": 20.428125000000023, "surface_net_solar_radiation": 18670692.0, "timestamp": "2021-04-01T00:00:00+00:00", "surface_latent_heat_flux": -1181264.0, "total_water_precipitation": 0.0, "relative_humidity": 41.964264, "surface_sensible_heat_flux": -8744005.0, "position": [43.6, 1.45], "wind_speed": 4.599381, "forecast": "2021-04-01T16:00:00+00:00", "maximum_temperature_at_2_metres": 20.97646500000002}, "geometry": {"type": "Point", "coordinates": [1.45, 43.6]}, "record_timestamp": "2021-04-01T00:00:00+00:00"}, {"datasetid": "arome-0025-sp1_sp2", "recordid": "arome_0025_sp1_sp2_sp3_lastgrib2-12966837", "fields": {"surface_net_thermal_radiation": -6841062.0, "downward_short_wave_radiation_flux": 19423072.0, "2_metre_temperature": 20.992334000000028, "dist": "0.0", "minimum_temperature_at_2_metres": 20.933496000000048, "surface_net_solar_radiation": 17202316.0, "timestamp": "2021-04-01T00:00:00+00:00", "surface_latent_heat_flux": -1057320.0, "total_water_precipitation": 0.0, "relative_humidity": 41.569557, "surface_sensible_heat_flux": -7968185.0, "position": [43.6, 1.45], "wind_speed": 4.587164, "forecast": "2021-04-01T15:00:00+00:00", "maximum_temperature_at_2_metres": 21.01870100000002}, "geometry": {"type": "Point", "coordinates": [1.45, 43.6]}, "record_timestamp": "2021-04-01T00:00:00+00:00"}, {"datasetid": "arome-0025-sp1_sp2", "recordid": "arome_0025_sp1_sp2_sp3_lastgrib2-12966836", "fields": {"surface_net_thermal_radiation": -6165265.0, "downward_short_wave_radiation_flux": 17108676.0, "2_metre_temperature": 20.946436000000006, "dist": "0.0", "minimum_temperature_at_2_metres": 20.33144500000003, "surface_net_solar_radiation": 15155326.0, "timestamp": "2021-04-01T00:00:00+00:00", "surface_latent_heat_flux": -906102.0, "total_water_precipitation": 0.0, "relative_humidity": 39.639912, "surface_sensible_heat_flux": -6935543.0, "position": [43.6, 1.45], "wind_speed": 4.75549, "forecast": "2021-04-01T14:00:00+00:00", "maximum_temperature_at_2_metres": 20.954492000000016}, "geometry": {"type": "Point", "coordinates": [1.45, 43.6]}, "record_timestamp": "2021-04-01T00:00:00+00:00"}, {"datasetid": "arome-0025-sp1_sp2", "recordid": "arome_0025_sp1_sp2_sp3_lastgrib2-12966835", "fields": {"surface_net_thermal_radiation": -5444784.0, "downward_short_wave_radiation_flux": 14367051.0, "2_metre_temperature": 20.336572000000047, "dist": "0.0", "minimum_temperature_at_2_metres": 19.360742000000016, "surface_net_solar_radiation": 12724603.0, "timestamp": "2021-04-01T00:00:00+00:00", "surface_latent_heat_flux": -738007.0, "total_water_precipitation": 0.0, "relative_humidity": 39.802261, "surface_sensible_heat_flux": -5723318.0, "position": [43.6, 1.45], "wind_speed": 5.043659, "forecast": "2021-04-01T13:00:00+00:00", "maximum_temperature_at_2_metres": 20.336572000000047}, "geometry": {"type": "Point", "coordinates": [1.45, 43.6]}, "record_timestamp": "2021-04-01T00:00:00+00:00"}, {"datasetid": "arome-0025-sp1_sp2", "recordid": "arome_0025_sp1_sp2_sp3_lastgrib2-12966834", "fields": {"surface_net_thermal_radiation": -4718734.0, "downward_short_wave_radiation_flux": 11405602.0, "2_metre_temperature": 19.363184000000047, "dist": "0.0", "minimum_temperature_at_2_metres": 18.059961000000044, "surface_net_solar_radiation": 10093314.0, "timestamp": "2021-04-01T00:00:00+00:00", "surface_latent_heat_flux": -568618.0, "total_water_precipitation": 0.0, "relative_humidity": 43.31168, "surface_sensible_heat_flux": -4424937.0, "position": [43.6, 1.45], "wind_speed": 5.044086, "forecast": "2021-04-01T12:00:00+00:00", "maximum_temperature_at_2_metres": 19.37392600000004}, "geometry": {"type": "Point", "coordinates": [1.45, 43.6]}, "record_timestamp": "2021-04-01T00:00:00+00:00"}, {"datasetid": "arome-0025-sp1_sp2", "recordid": "arome_0025_sp1_sp2_sp3_lastgrib2-12966833", "fields": {"surface_net_thermal_radiation": -4019241.0, "downward_short_wave_radiation_flux": 8440913.0, "2_metre_temperature": 18.035791000000017, "dist": "0.0", "minimum_temperature_at_2_metres": 16.575342000000035, "surface_net_solar_radiation": 7459583.0, "timestamp": "2021-04-01T00:00:00+00:00", "surface_latent_heat_flux": -410334.0, "total_water_precipitation": 0.0, "relative_humidity": 43.949879, "surface_sensible_heat_flux": -3172354.0, "position": [43.6, 1.45], "wind_speed": 5.324883, "forecast": "2021-04-01T11:00:00+00:00", "maximum_temperature_at_2_metres": 18.039697000000047}, "geometry": {"type": "Point", "coordinates": [1.45, 43.6]}, "record_timestamp": "2021-04-01T00:00:00+00:00"}, {"datasetid": "arome-0025-sp1_sp2", "recordid": "arome_0025_sp1_sp2_sp3_lastgrib2-12966832", "fields": {"surface_net_thermal_radiation": -3382514.0, "downward_short_wave_radiation_flux": 5682970.5, "2_metre_temperature": 16.551660000000027, "dist": "0.0", "minimum_temperature_at_2_metres": 14.950586000000044, "surface_net_solar_radiation": 5013722.0, "timestamp": "2021-04-01T00:00:00+00:00", "surface_latent_heat_flux": -267743.0, "total_water_precipitation": 0.0, "relative_humidity": 46.960171, "surface_sensible_heat_flux": -2033917.0, "position": [43.6, 1.45], "wind_speed": 5.686323, "forecast": "2021-04-01T10:00:00+00:00", "maximum_temperature_at_2_metres": 16.55361300000004}, "geometry": {"type": "Point", "coordinates": [1.45, 43.6]}, "record_timestamp": "2021-04-01T00:00:00+00:00"}, {"datasetid": "arome-0025-sp1_sp2", "recordid": "arome_0025_sp1_sp2_sp3_lastgrib2-12966831", "fields": {"surface_net_thermal_radiation": -2817839.0, "downward_short_wave_radiation_flux": 3332017.75, "2_metre_temperature": 14.90493200000003, "dist": "0.0", "minimum_temperature_at_2_metres": 13.321190999999999, "surface_net_solar_radiation": 2936562.0, "timestamp": "2021-04-01T00:00:00+00:00", "surface_latent_heat_flux": -154340.0, "total_water_precipitation": 0.0, "relative_humidity": 51.550377, "surface_sensible_heat_flux": -1121787.0, "position": [43.6, 1.45], "wind_speed": 5.513226, "forecast": "2021-04-01T09:00:00+00:00", "maximum_temperature_at_2_metres": 14.910059000000047}, "geometry": {"type": "Point", "coordinates": [1.45, 43.6]}, "record_timestamp": "2021-04-01T00:00:00+00:00"}, {"datasetid": "arome-0025-sp1_sp2", "recordid": "arome_0025_sp1_sp2_sp3_lastgrib2-12966830", "fields": {"surface_net_thermal_radiation": -2346308.0, "downward_short_wave_radiation_flux": 1553060.625, "2_metre_temperature": 13.28115200000002, "dist": "0.0", "minimum_temperature_at_2_metres": 11.818017999999995, "surface_net_solar_radiation": 1369340.0, "timestamp": "2021-04-01T00:00:00+00:00", "surface_latent_heat_flux": -73771.0, "total_water_precipitation": 0.0, "relative_humidity": 56.371552, "surface_sensible_heat_flux": -473589.0, "position": [43.6, 1.45], "wind_speed": 5.596728, "forecast": "2021-04-01T08:00:00+00:00", "maximum_temperature_at_2_metres": 13.286035000000027}, "geometry": {"type": "Point", "coordinates": [1.45, 43.6]}, "record_timestamp": "2021-04-01T00:00:00+00:00"}, {"datasetid": "arome-0025-sp1_sp2", "recordid": "arome_0025_sp1_sp2_sp3_lastgrib2-12966829", "fields": {"surface_net_thermal_radiation": -1966263.0, "downward_short_wave_radiation_flux": 449084.90625, "2_metre_temperature": 11.793115, "dist": "0.0", "minimum_temperature_at_2_metres": 11.101465000000019, "surface_net_solar_radiation": 393284.9375, "timestamp": "2021-04-01T00:00:00+00:00", "surface_latent_heat_flux": -25689.0, "total_water_precipitation": 0.0, "relative_humidity": 61.671902, "surface_sensible_heat_flux": -93326.0, "position": [43.6, 1.45], "wind_speed": 5.437989, "forecast": "2021-04-01T07:00:00+00:00", "maximum_temperature_at_2_metres": 11.793115}, "geometry": {"type": "Point", "coordinates": [1.45, 43.6]}, "record_timestamp": "2021-04-01T00:00:00+00:00"}, {"datasetid": "arome-0025-sp1_sp2", "recordid": "arome_0025_sp1_sp2_sp3_lastgrib2-12966828", "fields": {"surface_net_thermal_radiation": -1657222.0, "downward_short_wave_radiation_flux": 20272.0, "2_metre_temperature": 11.059229000000016, "dist": "0.0", "minimum_temperature_at_2_metres": 10.824854000000016, "surface_net_solar_radiation": 17852.0, "timestamp": "2021-04-01T00:00:00+00:00", "surface_latent_heat_flux": -4078.0, "total_water_precipitation": 0.0, "relative_humidity": 64.585106, "surface_sensible_heat_flux": 40112.0, "position": [43.6, 1.45], "wind_speed": 5.032876, "forecast": "2021-04-01T06:00:00+00:00", "maximum_temperature_at_2_metres": 11.06215800000001}, "geometry": {"type": "Point", "coordinates": [1.45, 43.6]}, "record_timestamp": "2021-04-01T00:00:00+00:00"}, {"datasetid": "arome-0025-sp1_sp2", "recordid": "arome_0025_sp1_sp2_sp3_lastgrib2-12966827", "fields": {"surface_net_thermal_radiation": -1380845.0, "downward_short_wave_radiation_flux": 0.0, "2_metre_temperature": 10.824121000000048, "dist": "0.0", "minimum_temperature_at_2_metres": 10.769434000000047, "surface_net_solar_radiation": 0.0, "timestamp": "2021-04-01T00:00:00+00:00", "surface_latent_heat_flux": -2202.0, "total_water_precipitation": 0.0, "relative_humidity": 70.479156, "surface_sensible_heat_flux": 5329.0, "position": [43.6, 1.45], "wind_speed": 5.306406, "forecast": "2021-04-01T05:00:00+00:00", "maximum_temperature_at_2_metres": 10.829492000000016}, "geometry": {"type": "Point", "coordinates": [1.45, 43.6]}, "record_timestamp": "2021-04-01T00:00:00+00:00"}, {"datasetid": "arome-0025-sp1_sp2", "recordid": "arome_0025_sp1_sp2_sp3_lastgrib2-12966826", "fields": {"surface_net_thermal_radiation": -1107658.0, "downward_short_wave_radiation_flux": 0.0, "2_metre_temperature": 10.824854000000016, "dist": "0.0", "minimum_temperature_at_2_metres": 10.82778300000001, "surface_net_solar_radiation": 0.0, "timestamp": "2021-04-01T00:00:00+00:00", "surface_latent_heat_flux": -1866.0, "total_water_precipitation": 0.0, "relative_humidity": 75.78698, "surface_sensible_heat_flux": -14437.0, "position": [43.6, 1.45], "wind_speed": 5.888755, "forecast": "2021-04-01T04:00:00+00:00", "maximum_temperature_at_2_metres": 11.439355000000035}, "geometry": {"type": "Point", "coordinates": [1.45, 43.6]}, "record_timestamp": "2021-04-01T00:00:00+00:00"}, {"datasetid": "arome-0025-sp1_sp2", "recordid": "arome_0025_sp1_sp2_sp3_lastgrib2-12966825", "fields": {"surface_net_thermal_radiation": -833989.0, "downward_short_wave_radiation_flux": 0.0, "2_metre_temperature": 11.446924000000024, "dist": "0.0", "minimum_temperature_at_2_metres": 11.440576000000021, "surface_net_solar_radiation": 0.0, "timestamp": "2021-04-01T00:00:00+00:00", "surface_latent_heat_flux": -1609.0, "total_water_precipitation": 0.0, "relative_humidity": 61.913383, "surface_sensible_heat_flux": -23211.0, "position": [43.6, 1.45], "wind_speed": 6.010469, "forecast": "2021-04-01T03:00:00+00:00", "maximum_temperature_at_2_metres": 11.580713000000003}, "geometry": {"type": "Point", "coordinates": [1.45, 43.6]}, "record_timestamp": "2021-04-01T00:00:00+00:00"}, {"datasetid": "arome-0025-sp1_sp2", "recordid": "arome_0025_sp1_sp2_sp3_lastgrib2-12966824", "fields": {"surface_net_thermal_radiation": -558518.625, "downward_short_wave_radiation_flux": 0.0, "2_metre_temperature": 11.581201000000021, "dist": "0.0", "minimum_temperature_at_2_metres": 11.580225000000041, "surface_net_solar_radiation": 0.0, "timestamp": "2021-04-01T00:00:00+00:00", "surface_latent_heat_flux": -1027.0, "total_water_precipitation": 0.0, "relative_humidity": 60.869076, "surface_sensible_heat_flux": -31966.0, "position": [43.6, 1.45], "wind_speed": 5.220592, "forecast": "2021-04-01T02:00:00+00:00", "maximum_temperature_at_2_metres": 11.65151400000002}, "geometry": {"type": "Point", "coordinates": [1.45, 43.6]}, "record_timestamp": "2021-04-01T00:00:00+00:00"}, {"datasetid": "arome-0025-sp1_sp2", "recordid": "arome_0025_sp1_sp2_sp3_lastgrib2-12966823", "fields": {"surface_net_thermal_radiation": -281153.5, "downward_short_wave_radiation_flux": 0.0, "2_metre_temperature": 11.650780999999995, "dist": "0.0", "minimum_temperature_at_2_metres": 11.655664000000002, "surface_net_solar_radiation": 0.0, "timestamp": "2021-04-01T00:00:00+00:00", "surface_latent_heat_flux": -519.0, "total_water_precipitation": 0.0, "relative_humidity": 60.614784, "surface_sensible_heat_flux": -25316.5, "position": [43.6, 1.45], "wind_speed": 4.768929, "forecast": "2021-04-01T01:00:00+00:00", "maximum_temperature_at_2_metres": 11.826563000000021}, "geometry": {"type": "Point", "coordinates": [1.45, 43.6]}, "record_timestamp": "2021-04-01T00:00:00+00:00"}, {"datasetid": "arome-0025-sp1_sp2", "recordid": "arome_0025_sp1_sp2_sp3_lastgrib2-12966822", "fields": {"wind_speed": 4.25876, "2_metre_temperature": 12.080713000000003, "dist": "0.0", "timestamp": "2021-04-01T00:00:00+00:00", "forecast": "2021-04-01T00:00:00+00:00", "relative_humidity": 58.112614, "position": [43.6, 1.45]}, "geometry": {"type": "Point", "coordinates": [1.45, 43.6]}, "record_timestamp": "2021-04-01T00:00:00+00:00"}]}